py_rocket_launch_live_client/__init__.py
py_rocket_launch_live_client/_version.py
py_rocket_launch_live_client/auth.py
py_rocket_launch_live_client/cursor.py
py_rocket_launch_live_client/module.py
py_rocket_launch_live_client/py.typed
py_rocket_launch_live_client/codes/__init__.py
py_rocket_launch_live_client/codes/countries.py
py_rocket_launch_live_client/codes/us_states.py
py_rocket_launch_live_client/get/__init__.py
py_rocket_launch_live_client/get/companies.py
py_rocket_launch_live_client/get/launches.py
py_rocket_launch_live_client/get/locations.py
py_rocket_launch_live_client/get/missions.py
py_rocket_launch_live_client/get/pads.py
py_rocket_launch_live_client/get/tags.py
py_rocket_launch_live_client/get/vehicles.py
py_rocket_launch_live_client-1.1.0.dist-info/LICENSE
py_rocket_launch_live_client-1.1.0.dist-info/METADATA
py_rocket_launch_live_client-1.1.0.dist-info/WHEEL
py_rocket_launch_live_client-1.1.0.dist-info/entry_points.txt
py_rocket_launch_live_client-1.1.0.dist-info/top_level.txt
py_rocket_launch_live_client-1.1.0.dist-info/RECORD
