Metadata-Version: 2.1
Name: py-rocket-launch-live-client
Version: 1.1.0
Summary: Python Client for RocketLaunchLive API
Home-page: http://github.com/arthur-clifford/py-rocket-lauch-live-client
Author: arthur-clifford
Author-email: artclifford@me.com
License: MIT
Classifier: Programming Language :: Python :: 3
Classifier: License :: OSI Approved :: MIT License
Classifier: Operating System :: OS Independent
Requires-Python: >=3.10, <4
License-File: LICENSE
Requires-Dist: pandas
Requires-Dist: requests
Provides-Extra: dev
Requires-Dist: bandit ==1.7.* ; extra == 'dev'
Requires-Dist: black ==23.* ; extra == 'dev'
Requires-Dist: build ==0.10.* ; extra == 'dev'
Requires-Dist: flake8 ==6.* ; extra == 'dev'
Requires-Dist: isort ==5.* ; extra == 'dev'
Requires-Dist: mypy ==1.5.* ; extra == 'dev'
Requires-Dist: pytest ==7.* ; extra == 'dev'
Requires-Dist: pytest-cov ==4.* ; extra == 'dev'
Requires-Dist: twine ==4.* ; extra == 'dev'
